macad/LICENSE
macad/__init__.py
macad/mac_changer.py
macad-1.0.4.dist-info/entry_points.txt
macad-1.0.4.dist-info/WHEEL
macad-1.0.4.dist-info/METADATA
macad-1.0.4.dist-info/RECORD
