Metadata-Version: 2.1
Name: macad
Version: 1.0.4
Summary: The Tool For Changing Your MAC Address for Any Interface
Home-page: https://github.com/DeepakDarkiee/macad.git
License: MIT
Keywords: mac-address,macad,mac-changer
Author: Deepak Patidar
Author-email: info.deepakpatidar@gmail.com
Requires-Python: >=3.6.0
Classifier: License :: OSI Approved :: MIT License
Classifier: Programming Language :: Python :: 3
Classifier: Programming Language :: Python :: 3.10
Classifier: Programming Language :: Python :: 3.6
Classifier: Programming Language :: Python :: 3.7
Classifier: Programming Language :: Python :: 3.8
Classifier: Programming Language :: Python :: 3.9
Project-URL: Repository, https://github.com/DeepakDarkiee/macad.git
